BSplineX.py
_BSplineXpy.so
include/BSplineX/exceptions.hpp
include/BSplineX/defines.hpp
include/BSplineX/types.hpp
include/BSplineX/bsplinex.hpp
include/BSplineX/knots/knots.hpp
include/BSplineX/knots/t_finder.hpp
include/BSplineX/knots/t_atter.hpp
include/BSplineX/knots/t_data.hpp
include/BSplineX/knots/t_padder.hpp
include/BSplineX/knots/t_extrapolator.hpp
include/BSplineX/control_points/c_padder.hpp
include/BSplineX/control_points/c_atter.hpp
include/BSplineX/control_points/c_data.hpp
include/BSplineX/control_points/control_points.hpp
include/BSplineX/bspline/bspline.hpp
include/BSplineX/bspline/bspline_types.hpp
include/BSplineX/bspline/bspline_factory.hpp
lib/cmake/BSplineX/BSplineXTargets.cmake
lib/cmake/BSplineX/BSplineXConfig.cmake
lib/cmake/BSplineX/BSplineXConfigVersion.cmake
bsplinex-0.1.0.dist-info/METADATA
bsplinex-0.1.0.dist-info/RECORD
bsplinex-0.1.0.dist-info/WHEEL
